{
    "treasure": [
        {
            "name": "wand",
            "namePretty": "Wand",
            "description": "Your trusty magic wand that has protected you through many a journey against magical foes.",
            "strength": "wand",
            "starting": true,
            "effect": "weapon"
        },
        {
            "name": "sword",
            "namePretty": "Sword",
            "description": "Your trusty sword that has cleaved through many a beast that would have seen you as dinner.",
            "strength": "sword",
            "starting": true,
            "effect": "weapon"
        },
        {
            "name": "automaticCrossbow",
            "namePretty": "Automatic Crossbow",
            "description": "A crossbow which continuously fires bolts so long as the trigger is held.",
            "strength": "automaticCrossbow",
            "starting": false,
            "found": false,
            "taken": false,
            "effect": "weapon"
        },
        {
            "name": "romanCandle",
            "namePretty": "Roman Candle",
            "description": "A wand-like object that emits a ball of greek fire when evoked.",
            "strength": "fire",
            "starting": false,
            "found": false,
            "taken": false,
            "effect": "weapon"
        },
        {
            "name": "phoenixBearMace",
            "namePretty": "Phoenix Bear Mace",
            "description": "An aluminum cylinder covered in warning labels. A firey blue growling bear face is plastard on the front. 'Keep Away from Eyes'",
            "strength": "toxic",
            "starting": false,
            "found": false,
            "taken": false,
            "effect": "weapon"
        },
        {
            "name": "bananaPeel",
            "namePretty": "Banana Peel",
            "description": "The peel of a banana, its insides seem unusually slippery.",
            "strength": "bananaPeel",
            "starting": false,
            "found": false,
            "taken": false,
            "effect": "weapon"
        },
        {
            "name": "handheldVacuumCleaner",
            "namePretty": "Handheld Vacuum Cleaner",
            "description": "Small but powerful little vacuum that runs on batteries.",
            "strength": "handheldVacuumCleaner",
            "starting": false,
            "found": false,
            "taken": false,
            "effect": "weapon"
        },
        {
            "name": "banefulButterknife",
            "namePretty": "Baneful Butterknife",
            "description": "A tiny blade that glints wickedly in the light.  Sharp enough to cut through anything like butter.  Watch your fingers!",
            "strength": "sword",
            "starting": false,
            "found": false,
            "taken": false,
            "effect": "weapon"
        },
        {
            "name": "cattleProd",
            "namePretty": "Cattle Prod",
            "description": "A thin black cylinder with two metal prongs sticking out of one end. Perfect for dealing with shapeshifters and mimics.",
            "strength": "cattleProd",
            "starting": false,
            "found": false,
            "taken": false,
            "effect": "weapon"
        },
        {
            "name": "readME",
            "namePretty": "readME",
            "description": "A document containing the wisdom of the ages as they pertain to version control with git.",
            "strength": "readME",
            "starting": false,
            "found": false,
            "taken": false,
            "effect": "weapon"
        },
        {
            "name": "heathPotion",
            "namePretty": "Health Potion",
            "description": "A marvel of medical science, this potion will heal 2 points of your vaguely defined injuries.",
            "strength": "none",
            "heal": 2,
            "starting": false,
            "found": false,
            "taken": false,
            "effect": "heal"
        },
        {
            "name": "lesserheathPotion",
            "namePretty": "Lesser Health Potion",
            "description": "A marvel of medical science, this potion will heal 1 point of your vaguely defined injuries.",
            "strength": "none",
            "heal": 1,
            "starting": false,
            "found": false,
            "taken": false,
            "effect": "heal"
        },
        {
            "name": "greaterheathPotion",
            "namePretty": "Greater Health Potion",
            "description": "A marvel of medical science, this potion will heal 3 points of your vaguely defined injuries.",
            "strength": "none",
            "heal": 3,
            "starting": false,
            "found": false,
            "taken": false,
            "effect": "heal"
        }
    ]
}